LICENSE
README.md
setup.py
dbfaker/__init__.py
dbfaker/__main__.py
dbfaker/cli.py
dbfaker/table2yml.py
dbfaker.egg-info/PKG-INFO
dbfaker.egg-info/SOURCES.txt
dbfaker.egg-info/dependency_links.txt
dbfaker.egg-info/entry_points.txt
dbfaker.egg-info/requires.txt
dbfaker.egg-info/top_level.txt
dbfaker.egg-info/zip-safe
dbfaker/common/__init__.py
dbfaker/common/database.py
dbfaker/common/db_helper.py
dbfaker/common/drivers.py
dbfaker/common/logger.py
dbfaker/common/setting.py
dbfaker/common/tools.py
dbfaker/nsqlparse/__init__.py
dbfaker/nsqlparse/mysql_create_table_lex.py
dbfaker/nsqlparse/mysql_create_table_yacc.py
dbfaker/utils/__init__.py
dbfaker/utils/constant.py
dbfaker/utils/faker_date_time.py
dbfaker/utils/faker_tool.py
dbfaker/utils/gendata.py
dbfaker/utils/generator.py
dbfaker/utils/init_project.py
test/test_gendata.py
test/test_mfaker.py
test/test_table2yml.py