Metadata-Version: 2.1
Name: dbfaker
Version: 1.2.3
Summary: 基于数据库层面批量生成有逻辑关联的数据
Home-page: https://gitee.com/guojongg/dbfaker
Author: Long Guo
Author-email: 565169745@qq.com
License: UNKNOWN
Platform: UNKNOWN
Classifier: Development Status :: 4 - Beta
Classifier: License :: OSI Approved :: BSD License
Classifier: Programming Language :: Python
Classifier: Programming Language :: Python :: 3
Classifier: Programming Language :: Python :: 3.5
Classifier: Programming Language :: Python :: 3.6
Classifier: Programming Language :: Python :: 3.7
Classifier: Topic :: Software Development :: Libraries
License-File: LICENSE
